epyseri/__init__.py
epyseri/integration/__init__.py
epyseri/integration/trident_trace/TridentTraceClient.py
epyseri/integration/trident_trace/__init__.py
epyseri/integration/trident_trace/auth.py
epyseri/integration/trident_trace/config.py
epyseri/integration/trident_trace/core.py
epyseri/integration/trident_trace/error.py
epyseri/integration/trident_trace/helper.py
epyseri/integration/trident_trace/schemas.py
epyseri/integration/trident_trace/settings.py
epyseri/integration/trident_trace/utils.py
epyseri-0.0.1.dist-info/METADATA
epyseri-0.0.1.dist-info/WHEEL
epyseri-0.0.1.dist-info/top_level.txt
epyseri-0.0.1.dist-info/RECORD
